pyjess/__init__.py
pyjess/_jess.pyi
pyjess/__main__.py
pyjess/py.typed
pyjess/_jess.pypy310-pp73-x86_64-linux-gnu.so
pyjess/_peekable.py
pyjess/_jess.pyx
pyjess/_io.py
pyjess/.gitignore
pyjess/cli.py
pyjess/CMakeLists.txt
pyjess/tests/__init__.py
pyjess/tests/utils.py
pyjess/tests/test_atom.py
pyjess/tests/test_molecule.py
pyjess/tests/test_jess.py
pyjess/tests/test_template.py
pyjess/tests/test_hit.py
pyjess/tests/test_template_atom.py
pyjess/tests/test_doctest.py
pyjess/tests/data/__init__.py
pyjess/tests/data/pdb1lnb.pdb
pyjess/tests/data/template_02.qry
pyjess/tests/data/1sur.qry
pyjess/tests/data/1AMY+1.3.3.txt
pyjess/tests/data/1AMY.cif
pyjess/tests/data/4.1.2.tpl
pyjess/tests/data/1.3.3.tpl
pyjess/tests/data/5ayx.EF.pdb
pyjess/tests/data/template_01.qry
pyjess/tests/data/1AMY.pdb
pyjess-0.9.1.dist-info/RECORD
pyjess-0.9.1.dist-info/WHEEL
pyjess-0.9.1.dist-info/METADATA
pyjess-0.9.1.dist-info/entry_points.txt
pyjess-0.9.1.dist-info/licenses/COPYING
