Metadata-Version: 2.1
Name: pyjess
Version: 0.9.1
Summary: Cython bindings and Python interface to JESS, a 3D template matching software.
Keywords: bioinformatics,structure,template,matching
Author-Email: Martin Larralde <martin.larralde@embl.de>, Raymund Hacket <r.e.hackett@lumc.nl>
License: MIT License
Classifier: Development Status :: 4 - Beta
Classifier: Intended Audience :: Developers
Classifier: Intended Audience :: Science/Research
Classifier: License :: OSI Approved :: MIT License
Classifier: Operating System :: OS Independent
Classifier: Programming Language :: C
Classifier: Programming Language :: Cython
Classifier: Programming Language :: Python :: 3.7
Classifier: Programming Language :: Python :: 3.8
Classifier: Programming Language :: Python :: 3.9
Classifier: Programming Language :: Python :: 3.10
Classifier: Programming Language :: Python :: 3.11
Classifier: Programming Language :: Python :: 3.12
Classifier: Programming Language :: Python :: 3.13
Classifier: Programming Language :: Python :: 3.14
Classifier: Programming Language :: Python :: Implementation :: CPython
Classifier: Programming Language :: Python :: Implementation :: PyPy
Classifier: Topic :: Scientific/Engineering :: Bio-Informatics
Classifier: Topic :: Scientific/Engineering :: Medical Science Apps.
Classifier: Typing :: Typed
Project-URL: Homepage, https://github.com/althonos/pyjess/
Project-URL: Documentation, https://pyjess.readthedocs.io/en/stable/
Project-URL: Bug tracker, https://github.com/althonos/pyjess/issues
Project-URL: Changelog, https://github.com/althonos/pyjess/blob/master/CHANGELOG.md
Project-URL: Coverage, https://codecov.io/gh/althonos/pyjess/
Project-URL: Builds, https://github.com/althonos/pyjess/actions
Project-URL: Pypi, https://pypi.org/project/pyjess
Project-URL: Piwheels, https://piwheels.org/project/pyjess/
Requires-Python: >=3.7
Provides-Extra: test
Provides-Extra: cif
Requires-Dist: importlib-resources; python_version < "3.9" and extra == "test"
Requires-Dist: gemmi~=0.7.0; extra == "cif"
